{
    "entities": [
        {
            "mentions": [
                {
                    "text": {
                        "beginOffset": 0,
                        "content": "米国"
                    },
                    "type": "PROPER"
                }
            ],
            "metadata": {
                "mid": "/m/09c7w0",
                "wikipedia_url": "https://en.wikipedia.org/wiki/United_States"
            },
            "name": "米国",
            "salience": 0.24431948,
            "type": "LOCATION"
        },
        {
            "mentions": [
                {
                    "text": {
                        "beginOffset": 6,
                        "content": "シカゴ府世界博覧会"
                    },
                    "type": "PROPER"
                }
            ],
            "metadata": {},
            "name": "シカゴ府世界博覧会",
            "salience": 0.21773301,
            "type": "EVENT"
        },
        {
            "mentions": [
                {
                    "text": {
                        "beginOffset": 69,
                        "content": "省ヨリ照会\t S0001/Mo099/0075\t 1891-12-20\t 件\t 公開\t 本郷"
                    },
                    "type": "PROPER"
                }
            ],
            "metadata": {},
            "name": "省ヨリ照会 S0001/Mo099/0075 1891-12-20 件 公開 本郷",
            "salience": 0.19023132,
            "type": "ORGANIZATION"
        },
        {
            "mentions": [
                {
                    "text": {
                        "beginOffset": 54,
                        "content": "取調ノ義"
                    },
                    "type": "PROPER"
                }
            ],
            "metadata": {},
            "name": "取調ノ義",
            "salience": 0.18638124,
            "type": "PERSON"
        },
        {
            "mentions": [
                {
                    "text": {
                        "beginOffset": 33,
                        "content": "出品ニ係ル費用"
                    },
                    "type": "COMMON"
                }
            ],
            "metadata": {},
            "name": "出品ニ係ル費用",
            "salience": 0.16133495,
            "type": "OTHER"
        }
    ],
    "language": "ja"
}