{
    "entities": [
        {
            "mentions": [
                {
                    "text": {
                        "beginOffset": 0,
                        "content": "文部大臣官房建築課長ヨリ医科大学付属医院皮膚科病室付属浴室建増工事竣成并領収ノ件\t S0001/Mo128/0015\t -05\t 件\t 公開\t 本郷"
                    },
                    "type": "PROPER"
                }
            ],
            "metadata": {},
            "name": "文部大臣官房建築課長ヨリ医科大学付属医院皮膚科病室付属浴室建増工事竣成并領収ノ件 S0001/Mo128/0015 -05 件 公開 本郷",
            "salience": 1,
            "type": "ORGANIZATION"
        }
    ],
    "language": "ja"
}