{
    "entities": [
        {
            "mentions": [
                {
                    "text": {
                        "beginOffset": 15,
                        "content": "原則"
                    },
                    "type": "COMMON"
                },
                {
                    "text": {
                        "beginOffset": 108,
                        "content": "原則"
                    },
                    "type": "COMMON"
                }
            ],
            "metadata": {},
            "name": "原則",
            "salience": 0.1535154,
            "type": "OTHER"
        },
        {
            "mentions": [
                {
                    "text": {
                        "beginOffset": 27,
                        "content": "和平"
                    },
                    "type": "COMMON"
                },
                {
                    "text": {
                        "beginOffset": 120,
                        "content": "和平"
                    },
                    "type": "COMMON"
                }
            ],
            "metadata": {},
            "name": "和平",
            "salience": 0.1535154,
            "type": "OTHER"
        },
        {
            "mentions": [
                {
                    "text": {
                        "beginOffset": 39,
                        "content": "転機"
                    },
                    "type": "COMMON"
                },
                {
                    "text": {
                        "beginOffset": 132,
                        "content": "転機"
                    },
                    "type": "COMMON"
                }
            ],
            "metadata": {},
            "name": "転機",
            "salience": 0.14975098,
            "type": "OTHER"
        },
        {
            "mentions": [
                {
                    "text": {
                        "beginOffset": 0,
                        "content": "民族自決"
                    },
                    "type": "COMMON"
                }
            ],
            "metadata": {},
            "name": "民族自決",
            "salience": 0.1003391,
            "type": "EVENT"
        },
        {
            "mentions": [
                {
                    "text": {
                        "beginOffset": 205,
                        "content": "ベトナム戦争"
                    },
                    "type": "PROPER"
                }
            ],
            "metadata": {
                "mid": "/m/07_nf",
                "wikipedia_url": "https://en.wikipedia.org/wiki/Vietnam_War"
            },
            "name": "ベトナム戦争",
            "salience": 0.06711092,
            "type": "EVENT"
        },
        {
            "mentions": [
                {
                    "text": {
                        "beginOffset": 60,
                        "content": "∽06-065\t アイテム\t 06-065\t 民族自決"
                    },
                    "type": "COMMON"
                }
            ],
            "metadata": {},
            "name": "∽06-065 アイテム 06-065 民族自決",
            "salience": 0.067048825,
            "type": "EVENT"
        },
        {
            "mentions": [
                {
                    "text": {
                        "beginOffset": 155,
                        "content": "朝日ジャーナル"
                    },
                    "type": "PROPER"
                }
            ],
            "metadata": {
                "mid": "/g/122sxfp4",
                "wikipedia_url": "https://ja.wikipedia.org/wiki/朝日ジャーナル"
            },
            "name": "朝日ジャーナル",
            "salience": 0.06483161,
            "type": "PERSON"
        },
        {
            "mentions": [
                {
                    "text": {
                        "beginOffset": 226,
                        "content": "朝日新聞社"
                    },
                    "type": "PROPER"
                }
            ],
            "metadata": {
                "mid": "/g/12240qw5",
                "wikipedia_url": "https://de.wikipedia.org/wiki/Asahi_Shimbun-sha"
            },
            "name": "朝日新聞社",
            "salience": 0.06315703,
            "type": "ORGANIZATION"
        },
        {
            "mentions": [
                {
                    "text": {
                        "beginOffset": 246,
                        "content": "ja"
                    },
                    "type": "PROPER"
                }
            ],
            "metadata": {},
            "name": "ja",
            "salience": 0.06315703,
            "type": "OTHER"
        },
        {
            "mentions": [
                {
                    "text": {
                        "beginOffset": 196,
                        "content": "平和"
                    },
                    "type": "COMMON"
                }
            ],
            "metadata": {},
            "name": "平和",
            "salience": 0.059838604,
            "type": "OTHER"
        },
        {
            "mentions": [
                {
                    "text": {
                        "beginOffset": 179,
                        "content": "特集"
                    },
                    "type": "COMMON"
                }
            ],
            "metadata": {},
            "name": "特集",
            "salience": 0.057735104,
            "type": "EVENT"
        }
    ],
    "language": "ja"
}