{
    "entities": [
        {
            "mentions": [
                {
                    "text": {
                        "beginOffset": 18,
                        "content": "審議"
                    },
                    "type": "COMMON"
                },
                {
                    "text": {
                        "beginOffset": 102,
                        "content": "審議"
                    },
                    "type": "COMMON"
                }
            ],
            "metadata": {},
            "name": "審議",
            "salience": 0.22444284,
            "type": "EVENT"
        },
        {
            "mentions": [
                {
                    "text": {
                        "beginOffset": 36,
                        "content": "社説"
                    },
                    "type": "COMMON"
                },
                {
                    "text": {
                        "beginOffset": 120,
                        "content": "社説"
                    },
                    "type": "COMMON"
                }
            ],
            "metadata": {},
            "name": "社説",
            "salience": 0.17052066,
            "type": "OTHER"
        },
        {
            "mentions": [
                {
                    "text": {
                        "beginOffset": 0,
                        "content": "建国記念日"
                    },
                    "type": "PROPER"
                }
            ],
            "metadata": {},
            "name": "建国記念日",
            "salience": 0.15196924,
            "type": "OTHER"
        },
        {
            "mentions": [
                {
                    "text": {
                        "beginOffset": 137,
                        "content": "朝日新聞"
                    },
                    "type": "PROPER"
                },
                {
                    "text": {
                        "beginOffset": 152,
                        "content": "朝日新聞社"
                    },
                    "type": "PROPER"
                }
            ],
            "metadata": {
                "mid": "/m/01ttwm",
                "wikipedia_url": "https://en.wikipedia.org/wiki/Asahi_Shimbun"
            },
            "name": "朝日新聞",
            "salience": 0.12269438,
            "type": "ORGANIZATION"
        },
        {
            "mentions": [
                {
                    "text": {
                        "beginOffset": 54,
                        "content": "05-235\t アイテム\t 05-235\t 建国記念日"
                    },
                    "type": "PROPER"
                }
            ],
            "metadata": {},
            "name": "05-235 アイテム 05-235 建国記念日",
            "salience": 0.11440087,
            "type": "EVENT"
        },
        {
            "mentions": [
                {
                    "text": {
                        "beginOffset": 172,
                        "content": "ja"
                    },
                    "type": "PROPER"
                }
            ],
            "metadata": {},
            "name": "ja",
            "salience": 0.09327763,
            "type": "ORGANIZATION"
        }
    ],
    "language": "ja"
}