{
    "entities": [
        {
            "mentions": [
                {
                    "text": {
                        "beginOffset": 33,
                        "content": "記事"
                    },
                    "type": "COMMON"
                },
                {
                    "text": {
                        "beginOffset": 386,
                        "content": "記事"
                    },
                    "type": "COMMON"
                }
            ],
            "metadata": {},
            "name": "記事",
            "salience": 0.1596828,
            "type": "WORK_OF_ART"
        },
        {
            "mentions": [
                {
                    "text": {
                        "beginOffset": 3,
                        "content": "マスメディア批判"
                    },
                    "type": "COMMON"
                },
                {
                    "text": {
                        "beginOffset": 356,
                        "content": "マスメディア批判"
                    },
                    "type": "COMMON"
                }
            ],
            "metadata": {},
            "name": "マスメディア批判",
            "salience": 0.1596828,
            "type": "EVENT"
        },
        {
            "mentions": [
                {
                    "text": {
                        "beginOffset": 207,
                        "content": "新聞研究所"
                    },
                    "type": "PROPER"
                }
            ],
            "metadata": {},
            "name": "新聞研究所",
            "salience": 0.0901977,
            "type": "ORGANIZATION"
        },
        {
            "mentions": [
                {
                    "text": {
                        "beginOffset": 80,
                        "content": "東京大学大学院情報学環図書室"
                    },
                    "type": "PROPER"
                }
            ],
            "metadata": {},
            "name": "東京大学大学院情報学環図書室",
            "salience": 0.07663283,
            "type": "ORGANIZATION"
        },
        {
            "mentions": [
                {
                    "text": {
                        "beginOffset": 123,
                        "content": "附属社会情報研究資料センター"
                    },
                    "type": "PROPER"
                }
            ],
            "metadata": {},
            "name": "附属社会情報研究資料センター",
            "salience": 0.058533456,
            "type": "OTHER"
        },
        {
            "mentions": [
                {
                    "text": {
                        "beginOffset": 248,
                        "content": "図書室"
                    },
                    "type": "COMMON"
                }
            ],
            "metadata": {},
            "name": "図書室",
            "salience": 0.055360284,
            "type": "WORK_OF_ART"
        },
        {
            "mentions": [
                {
                    "text": {
                        "beginOffset": 183,
                        "content": "小野秀雄"
                    },
                    "type": "PROPER"
                }
            ],
            "metadata": {
                "mid": "/g/121xjwn9",
                "wikipedia_url": "https://de.wikipedia.org/wiki/Ono_Hideo"
            },
            "name": "小野秀雄",
            "salience": 0.044202562,
            "type": "PERSON"
        },
        {
            "mentions": [
                {
                    "text": {
                        "beginOffset": 327,
                        "content": "移管"
                    },
                    "type": "COMMON"
                }
            ],
            "metadata": {},
            "name": "移管",
            "salience": 0.040062066,
            "type": "EVENT"
        },
        {
            "mentions": [
                {
                    "text": {
                        "beginOffset": 430,
                        "content": "211\t 147\t 福  博充\t 福  博充\t 新聞"
                    },
                    "type": "PROPER"
                }
            ],
            "metadata": {},
            "name": "211147 福 博充 福 博充 新聞",
            "salience": 0.03680589,
            "type": "PERSON"
        },
        {
            "mentions": [
                {
                    "text": {
                        "beginOffset": 258,
                        "content": "社会情報研究資料センター貴重資料保存スペース"
                    },
                    "type": "COMMON"
                }
            ],
            "metadata": {},
            "name": "社会情報研究資料センター貴重資料保存スペース",
            "salience": 0.029642953,
            "type": "OTHER"
        },
        {
            "mentions": [
                {
                    "text": {
                        "beginOffset": 490,
                        "content": "論考"
                    },
                    "type": "COMMON"
                }
            ],
            "metadata": {},
            "name": "論考",
            "salience": 0.028540885,
            "type": "OTHER"
        },
        {
            "mentions": [
                {
                    "text": {
                        "beginOffset": 413,
                        "content": "日比谷五郎"
                    },
                    "type": "PROPER"
                }
            ],
            "metadata": {},
            "name": "日比谷五郎",
            "salience": 0.027137073,
            "type": "PERSON"
        },
        {
            "mentions": [
                {
                    "text": {
                        "beginOffset": 603,
                        "content": "付箋"
                    },
                    "type": "COMMON"
                }
            ],
            "metadata": {},
            "name": "付箋",
            "salience": 0.026549717,
            "type": "OTHER"
        },
        {
            "mentions": [
                {
                    "text": {
                        "beginOffset": 583,
                        "content": "括\t M2階でG４"
                    },
                    "type": "PROPER"
                }
            ],
            "metadata": {},
            "name": "括 M2階でG4",
            "salience": 0.026306244,
            "type": "OTHER"
        },
        {
            "mentions": [
                {
                    "text": {
                        "beginOffset": 531,
                        "content": "週刊誌"
                    },
                    "type": "COMMON"
                }
            ],
            "metadata": {},
            "name": "週刊誌",
            "salience": 0.025735026,
            "type": "OTHER"
        },
        {
            "mentions": [
                {
                    "text": {
                        "beginOffset": 499,
                        "content": "講義"
                    },
                    "type": "COMMON"
                }
            ],
            "metadata": {},
            "name": "講義",
            "salience": 0.024683721,
            "type": "EVENT"
        },
        {
            "mentions": [
                {
                    "text": {
                        "beginOffset": 508,
                        "content": "学術研究内容"
                    },
                    "type": "COMMON"
                }
            ],
            "metadata": {},
            "name": "学術研究内容",
            "salience": 0.024683721,
            "type": "OTHER"
        },
        {
            "mentions": [
                {
                    "text": {
                        "beginOffset": 564,
                        "content": "見出し\t ja\t 束"
                    },
                    "type": "COMMON"
                }
            ],
            "metadata": {},
            "name": "見出し ja 束",
            "salience": 0.023920843,
            "type": "OTHER"
        },
        {
            "mentions": [
                {
                    "text": {
                        "beginOffset": 474,
                        "content": "雑誌"
                    },
                    "type": "COMMON"
                }
            ],
            "metadata": {},
            "name": "雑誌",
            "salience": 0.023671335,
            "type": "WORK_OF_ART"
        },
        {
            "mentions": [
                {
                    "text": {
                        "beginOffset": 620,
                        "content": "I-0004-0197-0047"
                    },
                    "type": "PROPER"
                }
            ],
            "metadata": {},
            "name": "I-0004-0197-0047",
            "salience": 0.017968107,
            "type": "CONSUMER_GOOD"
        }
    ],
    "language": "ja"
}