{
    "entities": [
        {
            "mentions": [
                {
                    "text": {
                        "beginOffset": 0,
                        "content": "各藩ヨリ出セシ貢進生海外遊学ノ件\t S0001/Mo025/0146\t 1878-02\t 件\t 公開\t 本郷\t 伺及"
                    },
                    "type": "PROPER"
                }
            ],
            "metadata": {},
            "name": "各藩ヨリ出セシ貢進生海外遊学ノ件 S0001/Mo025/0146 1878-02 件 公開 本郷 伺及",
            "salience": 0.5171765,
            "type": "ORGANIZATION"
        },
        {
            "mentions": [
                {
                    "text": {
                        "beginOffset": 104,
                        "content": "上申"
                    },
                    "type": "COMMON"
                }
            ],
            "metadata": {},
            "name": "上申",
            "salience": 0.48282346,
            "type": "OTHER"
        }
    ],
    "language": "ja"
}