{
    "entities": [
        {
            "mentions": [
                {
                    "text": {
                        "beginOffset": 0,
                        "content": "ソ連"
                    },
                    "type": "PROPER"
                },
                {
                    "text": {
                        "beginOffset": 156,
                        "content": "ソ連"
                    },
                    "type": "PROPER"
                }
            ],
            "metadata": {
                "mid": "/m/05vz3zq",
                "wikipedia_url": "https://en.wikipedia.org/wiki/Soviet_Union"
            },
            "name": "ソ連",
            "salience": 0.17205223,
            "type": "PERSON"
        },
        {
            "mentions": [
                {
                    "text": {
                        "beginOffset": 39,
                        "content": "国連軍縮小委　足なみそろわぬ西欧"
                    },
                    "type": "PROPER"
                },
                {
                    "text": {
                        "beginOffset": 195,
                        "content": "国連軍縮小委　足なみそろわぬ西欧"
                    },
                    "type": "PROPER"
                }
            ],
            "metadata": {},
            "name": "国連軍縮小委 足なみそろわぬ西欧",
            "salience": 0.17205223,
            "type": "LOCATION"
        },
        {
            "mentions": [
                {
                    "text": {
                        "beginOffset": 6,
                        "content": "関心"
                    },
                    "type": "COMMON"
                },
                {
                    "text": {
                        "beginOffset": 162,
                        "content": "関心"
                    },
                    "type": "COMMON"
                }
            ],
            "metadata": {},
            "name": "関心",
            "salience": 0.109381266,
            "type": "OTHER"
        },
        {
            "mentions": [
                {
                    "text": {
                        "beginOffset": 87,
                        "content": "側"
                    },
                    "type": "COMMON"
                }
            ],
            "metadata": {},
            "name": "側",
            "salience": 0.09969889,
            "type": "ORGANIZATION"
        },
        {
            "mentions": [
                {
                    "text": {
                        "beginOffset": 281,
                        "content": "ロンドン発　\t 朝日新聞"
                    },
                    "type": "PROPER"
                }
            ],
            "metadata": {},
            "name": "ロンドン発 朝日新聞",
            "salience": 0.09902667,
            "type": "EVENT"
        },
        {
            "mentions": [
                {
                    "text": {
                        "beginOffset": 96,
                        "content": "国連軍縮小委員会"
                    },
                    "type": "PROPER"
                },
                {
                    "text": {
                        "beginOffset": 252,
                        "content": "国連軍縮小委員会"
                    },
                    "type": "PROPER"
                }
            ],
            "metadata": {},
            "name": "国連軍縮小委員会",
            "salience": 0.09418975,
            "type": "ORGANIZATION"
        },
        {
            "mentions": [
                {
                    "text": {
                        "beginOffset": 316,
                        "content": "朝日新聞社"
                    },
                    "type": "PROPER"
                }
            ],
            "metadata": {
                "mid": "/m/01ttwm",
                "wikipedia_url": "https://en.wikipedia.org/wiki/Asahi_Shimbun"
            },
            "name": "朝日新聞社",
            "salience": 0.093807735,
            "type": "ORGANIZATION"
        },
        {
            "mentions": [
                {
                    "text": {
                        "beginOffset": 243,
                        "content": "側"
                    },
                    "type": "COMMON"
                }
            ],
            "metadata": {},
            "name": "側",
            "salience": 0.08653799,
            "type": "ORGANIZATION"
        },
        {
            "mentions": [
                {
                    "text": {
                        "beginOffset": 336,
                        "content": "ja"
                    },
                    "type": "PROPER"
                }
            ],
            "metadata": {},
            "name": "ja",
            "salience": 0.073253244,
            "type": "ORGANIZATION"
        }
    ],
    "language": "ja"
}