{
    "entities": [
        {
            "mentions": [
                {
                    "text": {
                        "beginOffset": 0,
                        "content": "朝日ジャーナル　Vol.11 No.24"
                    },
                    "type": "PROPER"
                }
            ],
            "metadata": {},
            "name": "朝日ジャーナル Vol.11 No.24",
            "salience": 0.28373048,
            "type": "ORGANIZATION"
        },
        {
            "mentions": [
                {
                    "text": {
                        "beginOffset": 59,
                        "content": "F0015/061\t 1969-06-15\t アイテム\t 小堀巌"
                    },
                    "type": "PROPER"
                }
            ],
            "metadata": {},
            "name": "F0015/061 1969-06-15 アイテム 小堀巌",
            "salience": 0.2613911,
            "type": "PERSON"
        },
        {
            "mentions": [
                {
                    "text": {
                        "beginOffset": 107,
                        "content": "公開\t 柏\t 紙"
                    },
                    "type": "COMMON"
                }
            ],
            "metadata": {},
            "name": "公開 柏 紙",
            "salience": 0.22975428,
            "type": "PERSON"
        },
        {
            "mentions": [
                {
                    "text": {
                        "beginOffset": 39,
                        "content": "造反教師他"
                    },
                    "type": "COMMON"
                }
            ],
            "metadata": {},
            "name": "造反教師他",
            "salience": 0.22512415,
            "type": "OTHER"
        }
    ],
    "language": "ja"
}