{
    "entities": [
        {
            "mentions": [
                {
                    "text": {
                        "beginOffset": 0,
                        "content": "外国教授給料ノ件\t S0001/Mo025/0151\t 1878\t 件\t 公開\t 本郷\t 伺及"
                    },
                    "type": "PROPER"
                }
            ],
            "metadata": {},
            "name": "外国教授給料ノ件 S0001/Mo025/0151 1878 件 公開 本郷 伺及",
            "salience": 0.52576286,
            "type": "ORGANIZATION"
        },
        {
            "mentions": [
                {
                    "text": {
                        "beginOffset": 77,
                        "content": "上申"
                    },
                    "type": "COMMON"
                }
            ],
            "metadata": {},
            "name": "上申",
            "salience": 0.47423714,
            "type": "OTHER"
        }
    ],
    "language": "ja"
}