{
    "entities": [
        {
            "mentions": [
                {
                    "text": {
                        "beginOffset": 0,
                        "content": "醫學部"
                    },
                    "type": "COMMON"
                }
            ],
            "metadata": {},
            "name": "醫學部",
            "salience": 0.53192174,
            "type": "ORGANIZATION"
        },
        {
            "mentions": [
                {
                    "text": {
                        "beginOffset": 9,
                        "content": "建物平面圖間席所用称呼等書入出來ニ付送付ノ件\t S0001/Mo066/0011\t 1882-02-20\t 件\t 公開\t 本郷\t 會計"
                    },
                    "type": "PROPER"
                }
            ],
            "metadata": {},
            "name": "建物平面圖間席所用称呼等書入出來ニ付送付ノ件 S0001/Mo066/0011 1882-02-20 件 公開 本郷 會計",
            "salience": 0.46807826,
            "type": "WORK_OF_ART"
        }
    ],
    "language": "ja"
}