{
    "entities": [
        {
            "mentions": [
                {
                    "text": {
                        "beginOffset": 3,
                        "content": "陸奥公試メモ〕"
                    },
                    "type": "PROPER"
                }
            ],
            "metadata": {},
            "name": "陸奥公試メモ〕",
            "salience": 0.17593056,
            "type": "WORK_OF_ART"
        },
        {
            "mentions": [
                {
                    "text": {
                        "beginOffset": 25,
                        "content": "〔計算メモ"
                    },
                    "type": "COMMON"
                }
            ],
            "metadata": {},
            "name": "〔計算メモ",
            "salience": 0.1429035,
            "type": "OTHER"
        },
        {
            "mentions": [
                {
                    "text": {
                        "beginOffset": 128,
                        "content": "東京大学柏図書館\t 2007\t text\t font\t paper\t design\t product\t angle\t diagram\t document\t drawing\t rectangle"
                    },
                    "type": "PROPER"
                }
            ],
            "metadata": {},
            "name": "東京大学柏図書館 2007 text font paper design product angle diagram document drawing rectangle",
            "salience": 0.114086196,
            "type": "ORGANIZATION"
        },
        {
            "mentions": [
                {
                    "text": {
                        "beginOffset": 285,
                        "content": "Mutsu"
                    },
                    "type": "PROPER"
                }
            ],
            "metadata": {
                "mid": "/m/03w0nd",
                "wikipedia_url": "https://en.wikipedia.org/wiki/Japanese_battleship_Mutsu"
            },
            "name": "Mutsu",
            "salience": 0.10798492,
            "type": "OTHER"
        },
        {
            "mentions": [
                {
                    "text": {
                        "beginOffset": 84,
                        "content": "陸奥変体 大6-6-12"
                    },
                    "type": "PROPER"
                }
            ],
            "metadata": {},
            "name": "陸奥変体 大6-6-12",
            "salience": 0.10542655,
            "type": "LOCATION"
        },
        {
            "mentions": [
                {
                    "text": {
                        "beginOffset": 77,
                        "content": "A125"
                    },
                    "type": "PROPER"
                }
            ],
            "metadata": {},
            "name": "A125",
            "salience": 0.09959466,
            "type": "CONSUMER_GOOD"
        },
        {
            "mentions": [
                {
                    "text": {
                        "beginOffset": 106,
                        "content": "提案"
                    },
                    "type": "COMMON"
                }
            ],
            "metadata": {},
            "name": "提案",
            "salience": 0.094665535,
            "type": "EVENT"
        },
        {
            "mentions": [
                {
                    "text": {
                        "beginOffset": 47,
                        "content": "船体重量"
                    },
                    "type": "COMMON"
                }
            ],
            "metadata": {},
            "name": "船体重量",
            "salience": 0.089213684,
            "type": "OTHER"
        },
        {
            "mentions": [
                {
                    "text": {
                        "beginOffset": 117,
                        "content": "主力艦"
                    },
                    "type": "COMMON"
                }
            ],
            "metadata": {},
            "name": "主力艦",
            "salience": 0.07019438,
            "type": "OTHER"
        }
    ],
    "language": "ja"
}