{
    "entities": [
        {
            "mentions": [
                {
                    "text": {
                        "beginOffset": 30,
                        "content": "態度"
                    },
                    "type": "COMMON"
                },
                {
                    "text": {
                        "beginOffset": 183,
                        "content": "態度"
                    },
                    "type": "COMMON"
                }
            ],
            "metadata": {},
            "name": "態度",
            "salience": 0.117843114,
            "type": "OTHER"
        },
        {
            "mentions": [
                {
                    "text": {
                        "beginOffset": 99,
                        "content": "攻撃誘発"
                    },
                    "type": "COMMON"
                },
                {
                    "text": {
                        "beginOffset": 252,
                        "content": "攻撃誘発"
                    },
                    "type": "COMMON"
                }
            ],
            "metadata": {},
            "name": "攻撃誘発",
            "salience": 0.10030847,
            "type": "EVENT"
        },
        {
            "mentions": [
                {
                    "text": {
                        "beginOffset": 21,
                        "content": "各国"
                    },
                    "type": "COMMON"
                },
                {
                    "text": {
                        "beginOffset": 174,
                        "content": "各国"
                    },
                    "type": "COMMON"
                }
            ],
            "metadata": {},
            "name": "各国",
            "salience": 0.09854536,
            "type": "LOCATION"
        },
        {
            "mentions": [
                {
                    "text": {
                        "beginOffset": 51,
                        "content": "小国　核武装"
                    },
                    "type": "PROPER"
                },
                {
                    "text": {
                        "beginOffset": 204,
                        "content": "小国　核武装"
                    },
                    "type": "PROPER"
                }
            ],
            "metadata": {},
            "name": "小国 核武装",
            "salience": 0.096867755,
            "type": "OTHER"
        },
        {
            "mentions": [
                {
                    "text": {
                        "beginOffset": 42,
                        "content": "欧州"
                    },
                    "type": "PROPER"
                },
                {
                    "text": {
                        "beginOffset": 195,
                        "content": "欧州"
                    },
                    "type": "PROPER"
                }
            ],
            "metadata": {
                "mid": "/m/02j9z",
                "wikipedia_url": "https://en.wikipedia.org/wiki/Europe"
            },
            "name": "欧州",
            "salience": 0.09394104,
            "type": "LOCATION"
        },
        {
            "mentions": [
                {
                    "text": {
                        "beginOffset": 0,
                        "content": "ＮＡＴＯ"
                    },
                    "type": "PROPER"
                }
            ],
            "metadata": {
                "mid": "/m/059dn",
                "wikipedia_url": "https://en.wikipedia.org/wiki/NATO"
            },
            "name": "NATO",
            "salience": 0.06641337,
            "type": "ORGANIZATION"
        },
        {
            "mentions": [
                {
                    "text": {
                        "beginOffset": 12,
                        "content": "会議"
                    },
                    "type": "COMMON"
                }
            ],
            "metadata": {},
            "name": "会議",
            "salience": 0.059846025,
            "type": "EVENT"
        },
        {
            "mentions": [
                {
                    "text": {
                        "beginOffset": 72,
                        "content": "強化"
                    },
                    "type": "COMMON"
                }
            ],
            "metadata": {},
            "name": "強化",
            "salience": 0.050605856,
            "type": "EVENT"
        },
        {
            "mentions": [
                {
                    "text": {
                        "beginOffset": 81,
                        "content": "疑問"
                    },
                    "type": "COMMON"
                },
                {
                    "text": {
                        "beginOffset": 234,
                        "content": "疑問"
                    },
                    "type": "COMMON"
                }
            ],
            "metadata": {},
            "name": "疑問",
            "salience": 0.048659943,
            "type": "OTHER"
        },
        {
            "mentions": [
                {
                    "text": {
                        "beginOffset": 90,
                        "content": "ソ連"
                    },
                    "type": "PROPER"
                },
                {
                    "text": {
                        "beginOffset": 243,
                        "content": "ソ連"
                    },
                    "type": "PROPER"
                }
            ],
            "metadata": {
                "mid": "/m/05vz3zq",
                "wikipedia_url": "https://en.wikipedia.org/wiki/Soviet_Union"
            },
            "name": "ソ連",
            "salience": 0.04745378,
            "type": "PERSON"
        },
        {
            "mentions": [
                {
                    "text": {
                        "beginOffset": 267,
                        "content": "心配\t ロンドン発　\t 朝日新聞"
                    },
                    "type": "PROPER"
                }
            ],
            "metadata": {},
            "name": "心配 ロンドン発 朝日新聞",
            "salience": 0.047236945,
            "type": "ORGANIZATION"
        },
        {
            "mentions": [
                {
                    "text": {
                        "beginOffset": 310,
                        "content": "朝日新聞社"
                    },
                    "type": "PROPER"
                }
            ],
            "metadata": {
                "mid": "/m/01ttwm",
                "wikipedia_url": "https://en.wikipedia.org/wiki/Asahi_Shimbun"
            },
            "name": "朝日新聞社",
            "salience": 0.047236945,
            "type": "ORGANIZATION"
        },
        {
            "mentions": [
                {
                    "text": {
                        "beginOffset": 114,
                        "content": "心配∽02-493\t アイテム\t 02-493\t ＮＡＴＯ会議"
                    },
                    "type": "PROPER"
                }
            ],
            "metadata": {},
            "name": "心配∽02-493 アイテム 02-493 NATO会議",
            "salience": 0.045997657,
            "type": "EVENT"
        },
        {
            "mentions": [
                {
                    "text": {
                        "beginOffset": 225,
                        "content": "強化"
                    },
                    "type": "COMMON"
                }
            ],
            "metadata": {},
            "name": "強化",
            "salience": 0.043152813,
            "type": "EVENT"
        },
        {
            "mentions": [
                {
                    "text": {
                        "beginOffset": 330,
                        "content": "ja"
                    },
                    "type": "PROPER"
                }
            ],
            "metadata": {},
            "name": "ja",
            "salience": 0.035890937,
            "type": "ORGANIZATION"
        }
    ],
    "language": "ja"
}