{
    "entities": [
        {
            "mentions": [
                {
                    "text": {
                        "beginOffset": 3,
                        "content": "講演"
                    },
                    "type": "COMMON"
                },
                {
                    "text": {
                        "beginOffset": 42,
                        "content": "講演"
                    },
                    "type": "COMMON"
                },
                {
                    "text": {
                        "beginOffset": 75,
                        "content": "講演"
                    },
                    "type": "COMMON"
                }
            ],
            "metadata": {},
            "name": "講演",
            "salience": 0.3359177,
            "type": "EVENT"
        },
        {
            "mentions": [
                {
                    "text": {
                        "beginOffset": 12,
                        "content": "草稿"
                    },
                    "type": "COMMON"
                }
            ],
            "metadata": {},
            "name": "草稿",
            "salience": 0.16288698,
            "type": "OTHER"
        },
        {
            "mentions": [
                {
                    "text": {
                        "beginOffset": 36,
                        "content": "各種"
                    },
                    "type": "COMMON"
                }
            ],
            "metadata": {},
            "name": "各種",
            "salience": 0.14108735,
            "type": "OTHER"
        },
        {
            "mentions": [
                {
                    "text": {
                        "beginOffset": 92,
                        "content": "東京大学柏図書館\t 2007\t text\t music\t font\t paper\t black and white\t document\t angle\t writing\t product\t diagram\t design\t line\t pattern"
                    },
                    "type": "PROPER"
                }
            ],
            "metadata": {},
            "name": "東京大学柏図書館 2007 text music font paper black and white document angle writing product diagram design line pattern",
            "salience": 0.13287319,
            "type": "ORGANIZATION"
        },
        {
            "mentions": [
                {
                    "text": {
                        "beginOffset": 84,
                        "content": "講義"
                    },
                    "type": "COMMON"
                }
            ],
            "metadata": {},
            "name": "講義",
            "salience": 0.11690249,
            "type": "EVENT"
        },
        {
            "mentions": [
                {
                    "text": {
                        "beginOffset": 54,
                        "content": "図表"
                    },
                    "type": "COMMON"
                }
            ],
            "metadata": {},
            "name": "図表",
            "salience": 0.110332265,
            "type": "PERSON"
        }
    ],
    "language": "ja"
}